bpdb/__init__.py
bpdb/bpdb.py
bpdb/main.py
bpdb-0.0.3.dist-info/METADATA
bpdb-0.0.3.dist-info/WHEEL
bpdb-0.0.3.dist-info/entry_points.txt
bpdb-0.0.3.dist-info/top_level.txt
bpdb-0.0.3.dist-info/RECORD
